LICENSE
README.rst
setup.py
NLPX.egg-info/PKG-INFO
NLPX.egg-info/SOURCES.txt
NLPX.egg-info/dependency_links.txt
NLPX.egg-info/not-zip-safe
NLPX.egg-info/requires.txt
NLPX.egg-info/top_level.txt
nlpx/__init__.py
nlpx/utils.py
nlpx/dataset/__init__.py
nlpx/dataset/_collector.py
nlpx/dataset/_dataset.py
nlpx/model/__init__.py
nlpx/model/classifier.py
nlpx/model/embedding.py
nlpx/model/wrapper.py
nlpx/tokenize/__init__.py
nlpx/tokenize/stats.py
nlpx/tokenize/utils.py
test/test.py