Metadata-Version: 2.1
Name: NLPX
Version: 2.0.6
Summary: A tool set for NLP. Text classification. Trainer. Tokenizer
Home-page: https://gitee.com/summry/nlpx
Author: summy
Author-email: fkfkfk2024@2925.com
License: UNKNOWN
Keywords: NLP,nlp,AI,llm,GPT,Machine learning,Deep learning,tokenize,torch
Platform: UNKNOWN
Requires-Python: >=3.6
License-File: LICENSE
